arulespy/__init__.py
arulespy/arules.py
arulespy/arulesViz.py
arulespy-0.1.4.dist-info/LICENSE
arulespy-0.1.4.dist-info/METADATA
arulespy-0.1.4.dist-info/WHEEL
arulespy-0.1.4.dist-info/top_level.txt
arulespy-0.1.4.dist-info/RECORD
