Metadata-Version: 2.1
Name: arulespy
Version: 0.1.4
Summary: Python interface to the R package arules
Home-page: https://github.com/mhahsler/arulespy
Author: Michael Hahsler
Author-email: mhahsler@lyle.smu.edu
Project-URL: Documentation, https://github.com/mhahsler/arulespy
Project-URL: Bug Reports, https://github.com/mhahsler/arulespy/issues
Project-URL: Source Code, https://github.com/mhahsler/arulespy
Keywords: association rules,frequent itemsets
Classifier: Development Status :: 4 - Beta
Classifier: Intended Audience :: Education
Classifier: Intended Audience :: Science/Research
Classifier: Programming Language :: Python :: 3
Classifier: Programming Language :: R
Classifier: Programming Language :: C++
Classifier: License :: OSI Approved :: GNU General Public License v3 (GPLv3)
Classifier: Operating System :: OS Independent
Classifier: Topic :: Scientific/Engineering :: Information Analysis
Requires-Python: >=3.8
License-File: LICENSE
Requires-Dist: pandas >1.5.3
Requires-Dist: numpy >=1.14.2
Requires-Dist: scipy >=1.10.1
Requires-Dist: rpy2 >=3.5.11
Provides-Extra: dev
Requires-Dist: check-manifest ; extra == 'dev'
